README.md
setup.py
gbjpy/__init__.py
gbjpy.egg-info/PKG-INFO
gbjpy.egg-info/SOURCES.txt
gbjpy.egg-info/dependency_links.txt
gbjpy.egg-info/top_level.txt