Metadata-Version: 2.1
Name: gbjpy
Version: 5.5.0
Summary: My python package
Home-page: UNKNOWN
Author: Ganesh Jejurkar
Author-email: jejurkarganesh1990@gmail.com
License: UNKNOWN
Platform: UNKNOWN
Classifier: Programming Language :: Python :: 3
Classifier: License :: OSI Approved :: MIT License
Classifier: Operating System :: OS Independent
Requires-Python: >=3.6
